MANIFEST.in
README.txt
setup.py
docs/HISTORY.txt
docs/LICENSE.txt
silvatheme/__init__.py
silvatheme.standardissue.egg-info/PKG-INFO
silvatheme.standardissue.egg-info/SOURCES.txt
silvatheme.standardissue.egg-info/dependency_links.txt
silvatheme.standardissue.egg-info/namespace_packages.txt
silvatheme.standardissue.egg-info/not-zip-safe
silvatheme.standardissue.egg-info/requires.txt
silvatheme.standardissue.egg-info/top_level.txt
silvatheme/standardissue/__init__.py
silvatheme/standardissue/configure.zcml
silvatheme/standardissue/standardissue.py
silvatheme/standardissue/standardissue_templates/layout.cpt
silvatheme/standardissue/static/default.css
silvatheme/standardissue/static/default.min.css
silvatheme/standardissue/static/favicon.ico
silvatheme/standardissue/static/license.txt
silvatheme/standardissue/static/images/favicon.ico
silvatheme/standardissue/static/images/img01.gif
silvatheme/standardissue/static/images/img02.gif
silvatheme/standardissue/static/images/img03.gif
silvatheme/standardissue/static/images/img04.jpg
silvatheme/standardissue/static/images/img05.gif
silvatheme/standardissue/static/images/img06.gif
silvatheme/standardissue/static/images/img07.gif
silvatheme/standardissue/static/images/img08.gif
silvatheme/standardissue/static/images/img09.gif
silvatheme/standardissue/static/images/img10.gif
silvatheme/standardissue/static/images/spacer.gif