Metadata-Version: 1.1
Name: silvatheme.standardissue
Version: 1.5
Summary: Standard Issue theme for Silva CMS
Home-page: https://github.com/silvacms/silvatheme.standardissue
Author: Infrae - Design by NodeThirtyThree
Author-email: info@infrae.com
License: BSD and Creative Commons
Keywords: silvatheme standardissue
Platform: UNKNOWN
Classifier: Framework :: Zope2
Classifier: License :: OSI Approved :: BSD License
Classifier: Programming Language :: Python
Classifier: Topic :: Software Development :: Libraries :: Python Modules
